{
  "image_name": "uploaded",
  "timestamp": "2026-04-22T22:14:44.932624",
  "total_time": 115.14116263389587,
  "best_overall_algo": "HYBRID-PA5",
  "best_overall_f": -35.68368728740387,
  "best_overall_entropy": 35.68368728740387,
  "results": {
    "GWO": {
      "entropy": 35.2116979146216,
      "time": 15.428690910339355,
      "metrics": {
        "psnr": 32.74424234392925,
        "ssim": 0.9303061093983692,
        "boundary_dsc": 0.2967390251663692
      }
    },
    "WOA": {
      "entropy": 35.52602655538257,
      "time": 14.866377830505371,
      "metrics": {
        "psnr": 33.1085918800006,
        "ssim": 0.9317213621541696,
        "boundary_dsc": 0.2977713491272171
      }
    },
    "PSO": {
      "entropy": 35.51202037857883,
      "time": 31.472243785858154,
      "metrics": {
        "psnr": 33.388115068424966,
        "ssim": 0.9345659424040137,
        "boundary_dsc": 0.29465460640228275
      }
    },
    "OTSU": {
      "entropy": 34.68598839944959,
      "time": 0.49677395820617676,
      "metrics": {
        "psnr": 34.477990424880595,
        "ssim": 0.9454831471219243,
        "boundary_dsc": 0.2861209775046228
      }
    },
    "HYBRID-PA5": {
      "entropy": 35.68368728740387,
      "time": 32.801812410354614,
      "metrics": {
        "psnr": 32.63476455658743,
        "ssim": 0.9244875010924576,
        "boundary_dsc": 0.30005727376861396
      }
    },
    "HYBRID-PA6": {
      "entropy": 35.57358008874824,
      "time": 16.07242751121521,
      "metrics": {
        "psnr": 33.20494027632406,
        "ssim": 0.9317788326334818,
        "boundary_dsc": 0.2981287662543609
      }
    }
  }
}