[
  {
    "image_id": "188025",
    "algorithm": "WOA",
    "algorithm_variant": "optimizer",
    "seed": 42,
    "k": 10,
    "boundary_dsc": 0.2685201729621556,
    "fe": 37.11818602730558,
    "best_f": -37.11690701941102,
    "psnr": 32.46344432160623,
    "ssim": 0.9030387240219766,
    "time": 13.803760766983032,
    "thresholds": [
      33,
      56,
      78,
      100,
      122,
      144,
      166,
      188,
      211,
      233
    ]
  },
  {
    "image_id": "188025",
    "algorithm": "WOA",
    "algorithm_variant": "optimizer",
    "seed": 43,
    "k": 10,
    "boundary_dsc": 0.2653655973054965,
    "fe": 37.08927478166899,
    "best_f": -37.08778169296599,
    "psnr": 32.4007471401947,
    "ssim": 0.9005602740918789,
    "time": 15.05438756942749,
    "thresholds": [
      32,
      59,
      81,
      104,
      125,
      146,
      167,
      189,
      211,
      233
    ]
  },
  {
    "image_id": "188025",
    "algorithm": "WOA",
    "algorithm_variant": "optimizer",
    "seed": 44,
    "k": 10,
    "boundary_dsc": 0.2698595883823812,
    "fe": 37.051246631261364,
    "best_f": -37.050051937761125,
    "psnr": 32.49093778417111,
    "ssim": 0.9014364564291117,
    "time": 15.01999568939209,
    "thresholds": [
      35,
      57,
      79,
      100,
      121,
      142,
      163,
      186,
      209,
      233
    ]
  },
  {
    "image_id": "188025",
    "algorithm": "WOA",
    "algorithm_variant": "optimizer",
    "seed": 45,
    "k": 10,
    "boundary_dsc": 0.26527468360430395,
    "fe": 37.06535652460433,
    "best_f": -37.06369442383729,
    "psnr": 32.157226679568595,
    "ssim": 0.8967238898946719,
    "time": 15.500280380249023,
    "thresholds": [
      28,
      54,
      79,
      104,
      126,
      148,
      170,
      192,
      213,
      234
    ]
  },
  {
    "image_id": "188025",
    "algorithm": "WOA",
    "algorithm_variant": "optimizer",
    "seed": 46,
    "k": 10,
    "boundary_dsc": 0.2671626005632732,
    "fe": 37.13665480144272,
    "best_f": -37.13531274087611,
    "psnr": 32.45228777707676,
    "ssim": 0.9036450660948567,
    "time": 14.186891317367554,
    "thresholds": [
      33,
      56,
      79,
      101,
      123,
      145,
      167,
      189,
      211,
      233
    ]
  }
]